codekit/__init__.py
codekit/codetools.py
codekit/eups.py
codekit/progressbar.py
codekit/pygithub.py
codekit/versiondb.py
codekit/cli/__init__.py
codekit/cli/github_auth.py
codekit/cli/github_decimate_org.py
codekit/cli/github_fork_org.py
codekit/cli/github_get_ratelimit.py
codekit/cli/github_list_repos.py
codekit/cli/github_mv_repos_to_team.py
codekit/cli/github_tag_release.py
codekit/cli/github_tag_teams.py
sqre_codekit-7.5.0.dist-info/LICENSE
sqre_codekit-7.5.0.dist-info/METADATA
sqre_codekit-7.5.0.dist-info/WHEEL
sqre_codekit-7.5.0.dist-info/entry_points.txt
sqre_codekit-7.5.0.dist-info/top_level.txt
sqre_codekit-7.5.0.dist-info/RECORD
