Metadata-Version: 2.1
Name: sqre-codekit
Version: 7.5.0
Summary: LSST Data Management SQuaRE code management tools
Home-page: https://github.com/lsst-sqre/sqre-codekit
Author: Frossie Economou
Author-email: frossie@lsst.org
License: MIT
Keywords: lsst
Platform: UNKNOWN
Classifier: Development Status :: 4 - Beta
Classifier: Programming Language :: Python :: 3.6
Classifier: License :: OSI Approved :: MIT License
Requires-Dist: MapGitConfig (==1.1)
Requires-Dist: progressbar2 (==3.37.1)
Requires-Dist: public (==1.0)
Requires-Dist: pygithub (==1.40a3)
Requires-Dist: pyyaml (>=5.1)
Requires-Dist: requests (<3.0.0,>=2.8.1)
